wechaty/__init__.py
wechaty/accessory.py
wechaty/config.py
wechaty/exceptions.py
wechaty/fake_puppet.py
wechaty/plugin.py
wechaty/schema.py
wechaty/types.py
wechaty/version.py
wechaty/wechaty.py
wechaty/ui/favicon.ico
wechaty/ui/index.html
wechaty/ui/css/292.a17f1e3e.css
wechaty/ui/css/51.326d003f.css
wechaty/ui/css/601.61159bb6.css
wechaty/ui/css/734.629e843b.css
wechaty/ui/css/734.629e843b.css.gz
wechaty/ui/css/757.1cd8ca34.css
wechaty/ui/css/app.b89e305d.css
wechaty/ui/css/chunk-elementPlus.9241cf00.css
wechaty/ui/css/chunk-elementPlus.9241cf00.css.gz
wechaty/ui/img/jsoneditor-icons.94cc3007.svg
wechaty/ui/img/logo.e60e87af.png
wechaty/ui/js/201.becf3ba9.js
wechaty/ui/js/201.becf3ba9.js.LICENSE.txt
wechaty/ui/js/201.becf3ba9.js.gz
wechaty/ui/js/292.29ea0095.js
wechaty/ui/js/298.42816f9a.js
wechaty/ui/js/51.9ab59b36.js
wechaty/ui/js/601.988705c2.js
wechaty/ui/js/601.988705c2.js.gz
wechaty/ui/js/734.d95a274e.js
wechaty/ui/js/734.d95a274e.js.LICENSE.txt
wechaty/ui/js/734.d95a274e.js.gz
wechaty/ui/js/757.7e3a4880.js
wechaty/ui/js/app.8911f1ac.js
wechaty/ui/js/app.8911f1ac.js.gz
wechaty/ui/js/chunk-elementPlus.ec108ffe.js
wechaty/ui/js/chunk-elementPlus.ec108ffe.js.gz
wechaty/ui/js/chunk-elementPlusIcon.85fb8ecc.js
wechaty/ui/js/chunk-elementPlusIcon.85fb8ecc.js.LICENSE.txt
wechaty/ui/js/chunk-elementPlusIcon.85fb8ecc.js.gz
wechaty/ui/js/chunk-vendors.f6c2068e.js
wechaty/ui/js/chunk-vendors.f6c2068e.js.LICENSE.txt
wechaty/ui/js/chunk-vendors.f6c2068e.js.gz
wechaty/user/__init__.py
wechaty/user/contact.py
wechaty/user/contact_self.py
wechaty/user/favorite.py
wechaty/user/friendship.py
wechaty/user/image.py
wechaty/user/message.py
wechaty/user/message.pyi
wechaty/user/mini_program.py
wechaty/user/room.py
wechaty/user/room.pyi
wechaty/user/room_invitation.py
wechaty/user/tag.py
wechaty/user/url_link.py
wechaty/utils/__init__.py
wechaty/utils/async_helper.py
wechaty/utils/data_util.py
wechaty/utils/date_util.py
wechaty/utils/link.py
wechaty/utils/qr_code.py
wechaty-0.10.7.dist-info/LICENSE
wechaty-0.10.7.dist-info/METADATA
wechaty-0.10.7.dist-info/NOTICE
wechaty-0.10.7.dist-info/WHEEL
wechaty-0.10.7.dist-info/top_level.txt
wechaty-0.10.7.dist-info/RECORD
