Metadata-Version: 2.1
Name: wechaty
Version: 0.10.7
Summary: Wechaty is a Conversational RPA SDK for Chatbot Makers
Home-page: https://github.com/wechaty/python-wechaty
Author: Jingjing WU (吴京京)
Author-email: wechaty@chatie.io
License: Apache-2.0
Classifier: Programming Language :: Python :: 3.7
Classifier: License :: OSI Approved :: Apache Software License
Classifier: Operating System :: OS Independent
License-File: LICENSE
License-File: NOTICE
Requires-Dist: pyee
Requires-Dist: requests
Requires-Dist: qrcode
Requires-Dist: lxml
Requires-Dist: wechaty-puppet (>=0.4.19)
Requires-Dist: wechaty-puppet-service (>=0.8.9)
Requires-Dist: quart
Requires-Dist: opengraph-py3
Requires-Dist: Quart-CORS
Requires-Dist: APScheduler
Requires-Dist: SQLAlchemy
Requires-Dist: PyGithub
